{"nodes": [{"id": "c_users_lenovo_documents_jiwoag1_jiwof_master_src_components_yoga_studio_tsx", "label": "yoga-studio.tsx", "file_type": "code", "source_file": "C:\\Users\\Lenovo\\Documents\\jiwoag1\\jiwof-master\\src\\components\\yoga-studio.tsx", "source_location": "L1"}, {"id": "components_yoga_studio_yogastudio", "label": "YogaStudio()", "file_type": "code", "source_file": "C:\\Users\\Lenovo\\Documents\\jiwoag1\\jiwof-master\\src\\components\\yoga-studio.tsx", "source_location": "L10"}], "edges": [{"source": "c_users_lenovo_documents_jiwoag1_jiwof_master_src_components_yoga_studio_tsx", "target": "react", "relation": "imports_from", "confidence": "EXTRACTED", "source_file": "C:\\Users\\Lenovo\\Documents\\jiwoag1\\jiwof-master\\src\\components\\yoga-studio.tsx", "source_location": "L3", "weight": 1.0}, {"source": "c_users_lenovo_documents_jiwoag1_jiwof_master_src_components_yoga_studio_tsx", "target": "lucide_react", "relation": "imports_from", "confidence": "EXTRACTED", "source_file": "C:\\Users\\Lenovo\\Documents\\jiwoag1\\jiwof-master\\src\\components\\yoga-studio.tsx", "source_location": "L4", "weight": 1.0}, {"source": "c_users_lenovo_documents_jiwoag1_jiwof_master_src_components_yoga_studio_tsx", "target": "components_yoga_studio_yogastudio", "relation": "contains", "confidence": "EXTRACTED", "source_file": "C:\\Users\\Lenovo\\Documents\\jiwoag1\\jiwof-master\\src\\components\\yoga-studio.tsx", "source_location": "L10", "weight": 1.0}], "raw_calls": [{"caller_nid": "components_yoga_studio_yogastudio", "callee": "useState", "is_member_call": false, "source_file": "C:\\Users\\Lenovo\\Documents\\jiwoag1\\jiwof-master\\src\\components\\yoga-studio.tsx", "source_location": "L11"}, {"caller_nid": "components_yoga_studio_yogastudio", "callee": "Nidra", "is_member_call": false, "source_file": "C:\\Users\\Lenovo\\Documents\\jiwoag1\\jiwof-master\\src\\components\\yoga-studio.tsx", "source_location": "L143"}, {"caller_nid": "components_yoga_studio_yogastudio", "callee": "Praktik", "is_member_call": false, "source_file": "C:\\Users\\Lenovo\\Documents\\jiwoag1\\jiwof-master\\src\\components\\yoga-studio.tsx", "source_location": "L171"}, {"caller_nid": "components_yoga_studio_yogastudio", "callee": "Hatha", "is_member_call": false, "source_file": "C:\\Users\\Lenovo\\Documents\\jiwoag1\\jiwof-master\\src\\components\\yoga-studio.tsx", "source_location": "L196"}, {"caller_nid": "components_yoga_studio_yogastudio", "callee": "Postnatal", "is_member_call": false, "source_file": "C:\\Users\\Lenovo\\Documents\\jiwoag1\\jiwof-master\\src\\components\\yoga-studio.tsx", "source_location": "L232"}]}